xicorpy/__init__.py
xicorpy/_utils.py
xicorpy/conditional_dependence.py
xicorpy/correlation.py
xicorpy/foci.py
xicorpy-0.6.dist-info/LICENSE
xicorpy-0.6.dist-info/METADATA
xicorpy-0.6.dist-info/WHEEL
xicorpy-0.6.dist-info/RECORD
