Metadata-Version: 2.1
Name: xicorpy
Version: 0.6
Summary: Python implementation of Chatterjee's Rank Correlation, its modifications, and other offshoots
Home-page: https://swarnakumar.github.io/xicorpy
License: MIT
Author: Swarna Vallabhaneni
Author-email: swarnakumar@gmail.com
Maintainer: Swarna Vallabhaneni
Maintainer-email: swarnakumar@gmail.com
Requires-Python: >=3.9,<3.13
Classifier: Development Status :: 4 - Beta
Classifier: Intended Audience :: Developers
Classifier: Intended Audience :: Science/Research
Classifier: License :: OSI Approved :: MIT License
Classifier: Programming Language :: Python :: 3
Classifier: Programming Language :: Python :: 3.9
Classifier: Programming Language :: Python :: 3.10
Classifier: Programming Language :: Python :: 3.11
Classifier: Programming Language :: Python :: 3.12
Classifier: Topic :: Scientific/Engineering
Classifier: Topic :: Scientific/Engineering :: Information Analysis
Classifier: Topic :: Software Development :: Libraries
Classifier: Topic :: Software Development :: Libraries :: Python Modules
Provides-Extra: docs
Provides-Extra: typings
Requires-Dist: mkdocs-material (>=9.5,<9.6) ; extra == "docs"
Requires-Dist: mkdocstrings[python] (>=0.25,<0.26) ; extra == "docs"
Requires-Dist: mypy (==1.11) ; extra == "typings"
Requires-Dist: numpy (>=2,<3)
Requires-Dist: pandas (>=2.2,<3.0)
Requires-Dist: scikit-learn (>=1.5,<2.0)
Project-URL: Repository, https://github.com/swarnakumar/xicorpy
